trame/__init__.py
trame/modules/__init__.py
trame/modules/dockview.py
trame/widgets/__init__.py
trame/widgets/dockview.py
trame_dockview/__init__.py
trame_dockview/module/__init__.py
trame_dockview/module/serve/style.css
trame_dockview/module/serve/trame_dockview.umd.js
trame_dockview/widgets/__init__.py
trame_dockview/widgets/dockview.py
trame_dockview-1.2.2.dist-info/METADATA
trame_dockview-1.2.2.dist-info/WHEEL
trame_dockview-1.2.2.dist-info/licenses/LICENSE
trame_dockview-1.2.2.dist-info/RECORD
