Metadata-Version: 2.4
Name: trame-dockview
Version: 1.2.2
Summary: Trame wrapper to a Docking Layout Manager
Author: Kitware Inc.
License: MIT License
License-File: LICENSE
Keywords: Application,Framework,Interactive,Python,Web
Classifier: Development Status :: 5 - Production/Stable
Classifier: Environment :: Web Environment
Classifier: License :: OSI Approved :: MIT License
Classifier: Natural Language :: English
Classifier: Operating System :: OS Independent
Classifier: Programming Language :: Python :: 3 :: Only
Classifier: Topic :: Software Development :: Libraries :: Application Frameworks
Classifier: Topic :: Software Development :: Libraries :: Python Modules
Requires-Python: >=3.10
Requires-Dist: trame-client>=3.9.1
Provides-Extra: dev
Requires-Dist: nox; extra == 'dev'
Requires-Dist: pre-commit; extra == 'dev'
Requires-Dist: pytest-cov>=3; extra == 'dev'
Requires-Dist: pytest>=6; extra == 'dev'
Requires-Dist: ruff; extra == 'dev'
